Metadata-Version: 2.1
Name: simpol
Version: 0.0.2
Summary: A simpol package for you
Home-page: UNKNOWN
Author: Mohammed Daniyal
Author-email: danides450@gmail.com
License: UNKNOWN
Keywords: python,easy,effiecient
Platform: UNKNOWN
Classifier: Intended Audience :: Developers
Classifier: Programming Language :: Python :: 3
Classifier: Operating System :: Unix
Classifier: Operating System :: MacOS :: MacOS X
Classifier: Operating System :: Microsoft :: Windows
License-File: LICENSE
